dnsCapture/__init__.py
dnsCapture/dnsCapture.py
dnsCapture-1.1.1.dist-info/LICENSE
dnsCapture-1.1.1.dist-info/METADATA
dnsCapture-1.1.1.dist-info/WHEEL
dnsCapture-1.1.1.dist-info/top_level.txt
dnsCapture-1.1.1.dist-info/RECORD
