Metadata-Version: 2.1
Name: dnsCapture
Version: 1.1.1
Summary: a python packet to capture all DNS traffic
Home-page: https://github.com/j0ck3r2004/dnsCapture
Author: Vasilis Manthelas
Author-email: vasilismanthelas2004@gmail.com
License: UNKNOWN
Platform: UNKNOWN
Classifier: Programming Language :: Python :: 3
Classifier: License :: OSI Approved :: MIT License
Classifier: Operating System :: OS Independent
